Classfile /F:/it_course/daydream/jvm-deep/target/classes/cn/dbdj1201/jvm/cap9/MethodInnerStrucTest.class
  Last modified 2020-7-18; size 1772 bytes
  MD5 checksum 9ea94703a02146adae2c23e4a4fbd6d2
  Compiled from "MethodInnerStrucTest.java"
public class cn.dbdj1201.jvm.cap9.MethodInnerStrucTest extends java.lang.Object implements java.lang.Comparable<java.lang.String>, java.io.Serializable
  minor version: 0
  major version: 52
  flags: ACC_PUBLIC, ACC_SUPER
Constant pool:
   #1 = Methodref          #19.#57        // java/lang/Object."<init>":()V
   #2 = Fieldref           #18.#58        // cn/dbdj1201/jvm/cap9/MethodInnerStrucTest.num:I
   #3 = Fieldref           #59.#60        // java/lang/System.out:Ljava/io/PrintStream;
   #4 = Class              #61            // java/lang/StringBuilder
   #5 = Methodref          #4.#57         // java/lang/StringBuilder."<init>":()V
   #6 = String             #62            // count =
   #7 = Methodref          #4.#63         // java/lang/StringBuilder.append:(Ljava/lang/String;)Ljava/lang/StringBuilder;
   #8 = Methodref          #4.#64         // java/lang/StringBuilder.append:(I)Ljava/lang/StringBuilder;
   #9 = Methodref          #4.#65         // java/lang/StringBuilder.toString:()Ljava/lang/String;
  #10 = Methodref          #66.#67        // java/io/PrintStream.println:(Ljava/lang/String;)V
  #11 = Class              #68            // java/lang/Exception
  #12 = Methodref          #11.#69        // java/lang/Exception.printStackTrace:()V
  #13 = String             #70            //
  #14 = Class              #71            // java/lang/String
  #15 = Methodref          #18.#72        // cn/dbdj1201/jvm/cap9/MethodInnerStrucTest.compareTo:(Ljava/lang/String;)I
  #16 = String             #73            // 测试方法的内部结构
  #17 = Fieldref           #18.#74        // cn/dbdj1201/jvm/cap9/MethodInnerStrucTest.words:Ljava/lang/String;
  #18 = Class              #75            // cn/dbdj1201/jvm/cap9/MethodInnerStrucTest
  #19 = Class              #76            // java/lang/Object
  #20 = Class              #77            // java/lang/Comparable
  #21 = Class              #78            // java/io/Serializable
  #22 = Utf8               num
  #23 = Utf8               I
  #24 = Utf8               words
  #25 = Utf8               Ljava/lang/String;
  #26 = Utf8               <init>
  #27 = Utf8               ()V
  #28 = Utf8               Code
  #29 = Utf8               LineNumberTable
  #30 = Utf8               LocalVariableTable
  #31 = Utf8               this
  #32 = Utf8               Lcn/dbdj1201/jvm/cap9/MethodInnerStrucTest;
  #33 = Utf8               test1
  #34 = Utf8               count
  #35 = Utf8               test2
  #36 = Utf8               (I)I
  #37 = Utf8               value
  #38 = Utf8               e
  #39 = Utf8               Ljava/lang/Exception;
  #40 = Utf8               cal
  #41 = Utf8               result
  #42 = Utf8               StackMapTable
  #43 = Class              #68            // java/lang/Exception
  #44 = Utf8               compareTo
  #45 = Utf8               (Ljava/lang/String;)I
  #46 = Utf8               o
  #47 = Utf8               main
  #48 = Utf8               ([Ljava/lang/String;)V
  #49 = Utf8               args
  #50 = Utf8               [Ljava/lang/String;
  #51 = Utf8               (Ljava/lang/Object;)I
  #52 = Utf8               <clinit>
  #53 = Utf8               Signature
  #54 = Utf8               Ljava/lang/Object;Ljava/lang/Comparable<Ljava/lang/String;>;Ljava/io/Serializable;
  #55 = Utf8               SourceFile
  #56 = Utf8               MethodInnerStrucTest.java
  #57 = NameAndType        #26:#27        // "<init>":()V
  #58 = NameAndType        #22:#23        // num:I
  #59 = Class              #79            // java/lang/System
  #60 = NameAndType        #80:#81        // out:Ljava/io/PrintStream;
  #61 = Utf8               java/lang/StringBuilder
  #62 = Utf8               count =
  #63 = NameAndType        #82:#83        // append:(Ljava/lang/String;)Ljava/lang/StringBuilder;
  #64 = NameAndType        #82:#84        // append:(I)Ljava/lang/StringBuilder;
  #65 = NameAndType        #85:#86        // toString:()Ljava/lang/String;
  #66 = Class              #87            // java/io/PrintStream
  #67 = NameAndType        #88:#89        // println:(Ljava/lang/String;)V
  #68 = Utf8               java/lang/Exception
  #69 = NameAndType        #90:#27        // printStackTrace:()V
  #70 = Utf8
  #71 = Utf8               java/lang/String
  #72 = NameAndType        #44:#45        // compareTo:(Ljava/lang/String;)I
  #73 = Utf8               测试方法的内部结构
  #74 = NameAndType        #24:#25        // words:Ljava/lang/String;
  #75 = Utf8               cn/dbdj1201/jvm/cap9/MethodInnerStrucTest
  #76 = Utf8               java/lang/Object
  #77 = Utf8               java/lang/Comparable
  #78 = Utf8               java/io/Serializable
  #79 = Utf8               java/lang/System
  #80 = Utf8               out
  #81 = Utf8               Ljava/io/PrintStream;
  #82 = Utf8               append
  #83 = Utf8               (Ljava/lang/String;)Ljava/lang/StringBuilder;
  #84 = Utf8               (I)Ljava/lang/StringBuilder;
  #85 = Utf8               toString
  #86 = Utf8               ()Ljava/lang/String;
  #87 = Utf8               java/io/PrintStream
  #88 = Utf8               println
  #89 = Utf8               (Ljava/lang/String;)V
  #90 = Utf8               printStackTrace
{
  private int num;
    descriptor: I
    flags: ACC_PRIVATE

  private static java.lang.String words;
    descriptor: Ljava/lang/String;
    flags: ACC_PRIVATE, ACC_STATIC

  public cn.dbdj1201.jvm.cap9.MethodInnerStrucTest();
    descriptor: ()V
    flags: ACC_PUBLIC
    Code:
      stack=2, locals=1, args_size=1
         0: aload_0
         1: invokespecial #1                  // Method java/lang/Object."<init>":()V
         4: aload_0
         5: bipush        10
         7: putfield      #2                  // Field num:I
        10: return
      LineNumberTable:
        line 9: 0
        line 10: 4
      LocalVariableTable:
        Start  Length  Slot  Name   Signature
            0      11     0  this   Lcn/dbdj1201/jvm/cap9/MethodInnerStrucTest;

  public void test1();
    descriptor: ()V
    flags: ACC_PUBLIC
    Code:
      stack=3, locals=2, args_size=1
         0: bipush        20
         2: istore_1
         3: getstatic     #3                  // Field java/lang/System.out:Ljava/io/PrintStream;
         6: new           #4                  // class java/lang/StringBuilder
         9: dup
        10: invokespecial #5                  // Method java/lang/StringBuilder."<init>":()V
        13: ldc           #6                  // String count =
        15: invokevirtual #7                  // Method java/lang/StringBuilder.append:(Ljava/lang/String;)Ljava/lang/StringBuilder;
        18: iload_1
        19: invokevirtual #8                  // Method java/lang/StringBuilder.append:(I)Ljava/lang/StringBuilder;
        22: invokevirtual #9                  // Method java/lang/StringBuilder.toString:()Ljava/lang/String;
        25: invokevirtual #10                 // Method java/io/PrintStream.println:(Ljava/lang/String;)V
        28: return
      LineNumberTable:
        line 15: 0
        line 16: 3
        line 17: 28
      LocalVariableTable:
        Start  Length  Slot  Name   Signature
            0      29     0  this   Lcn/dbdj1201/jvm/cap9/MethodInnerStrucTest;
            3      26     1 count   I

  public static int test2(int);
    descriptor: (I)I
    flags: ACC_PUBLIC, ACC_STATIC
    Code:
      stack=2, locals=3, args_size=1
         0: iconst_0
         1: istore_1
         2: bipush        30
         4: istore_2
         5: iload_2
         6: iload_0
         7: idiv
         8: istore_1
         9: goto          17
        12: astore_2
        13: aload_2
        14: invokevirtual #12                 // Method java/lang/Exception.printStackTrace:()V
        17: iload_1
        18: ireturn
      Exception table:
         from    to  target type
             2     9    12   Class java/lang/Exception
      LineNumberTable:
        line 20: 0
        line 22: 2
        line 23: 5
        line 26: 9
        line 24: 12
        line 25: 13
        line 27: 17
      LocalVariableTable:
        Start  Length  Slot  Name   Signature
            5       4     2 value   I
           13       4     2     e   Ljava/lang/Exception;
            0      19     0   cal   I
            2      17     1 result   I
      StackMapTable: number_of_entries = 2
        frame_type = 255 /* full_frame */
          offset_delta = 12
          locals = [ int, int ]
          stack = [ class java/lang/Exception ]
        frame_type = 4 /* same */

  public int compareTo(java.lang.String);
    descriptor: (Ljava/lang/String;)I
    flags: ACC_PUBLIC
    Code:
      stack=1, locals=2, args_size=2
         0: iconst_0
         1: ireturn
      LineNumberTable:
        line 32: 0
      LocalVariableTable:
        Start  Length  Slot  Name   Signature
            0       2     0  this   Lcn/dbdj1201/jvm/cap9/MethodInnerStrucTest;
            0       2     1     o   Ljava/lang/String;

  public static void main(java.lang.String[]);
    descriptor: ([Ljava/lang/String;)V
    flags: ACC_PUBLIC, ACC_STATIC
    Code:
      stack=2, locals=1, args_size=1
         0: getstatic     #3                  // Field java/lang/System.out:Ljava/io/PrintStream;
         3: ldc           #13                 // String
         5: invokevirtual #10                 // Method java/io/PrintStream.println:(Ljava/lang/String;)V
         8: return
      LineNumberTable:
        line 36: 0
        line 37: 8
      LocalVariableTable:
        Start  Length  Slot  Name   Signature
            0       9     0  args   [Ljava/lang/String;

  public int compareTo(java.lang.Object);
    descriptor: (Ljava/lang/Object;)I
    flags: ACC_PUBLIC, ACC_BRIDGE, ACC_SYNTHETIC
    Code:
      stack=2, locals=2, args_size=2
         0: aload_0
         1: aload_1
         2: checkcast     #14                 // class java/lang/String
         5: invokevirtual #15                 // Method compareTo:(Ljava/lang/String;)I
         8: ireturn
      LineNumberTable:
        line 9: 0
      LocalVariableTable:
        Start  Length  Slot  Name   Signature
            0       9     0  this   Lcn/dbdj1201/jvm/cap9/MethodInnerStrucTest;

  static {};
    descriptor: ()V
    flags: ACC_STATIC
    Code:
      stack=1, locals=0, args_size=0
         0: ldc           #16                 // String 测试方法的内部结构
         2: putstatic     #17                 // Field words:Ljava/lang/String;
         5: return
      LineNumberTable:
        line 11: 0
}
Signature: #54                          // Ljava/lang/Object;Ljava/lang/Comparable<Ljava/lang/String;>;Ljava/io/Serializable;
SourceFile: "MethodInnerStrucTest.java"
